[
    {
        "securityNumber": "273011",
        "securityName": "נייס",
        "symbol": "נייס"
    },
    {
        "securityNumber": "691212",
        "securityName": "דיסקונט       א",
        "symbol": "דסקנט"
    },
    {
        "securityNumber": "662577",
        "securityName": "פועלים",
        "symbol": "פעלים"
    },
    {
        "securityNumber": "629014",
        "securityName": "טבע",
        "symbol": "טבע"
    },
    {
        "securityNumber": "604611",
        "securityName": "לאומי",
        "symbol": "לאומי"
    },
    {
        "securityNumber": "281014",
        "securityName": "איי.סי.אל",
        "symbol": "איסל"
    },
    {
        "securityNumber": "695437",
        "securityName": "מזרחי טפחות",
        "symbol": "מזטפ"
    },
    {
        "securityNumber": "1082379",
        "securityName": "טאואר",
        "symbol": "טאואר"
    },
    {
        "securityNumber": "1081124",
        "securityName": "אלביט מערכות",
        "symbol": "אלבמע"
    },
    {
        "securityNumber": "1134402",
        "securityName": "אורמת טכנו",
        "symbol": "ארמת"
    },
    {
        "securityNumber": "230011",
        "securityName": "בזק",
        "symbol": "בזק"
    },
    {
        "securityNumber": "1119478",
        "securityName": "עזריאלי קבוצה",
        "symbol": "עזרל"
    },
    {
        "securityNumber": "593038",
        "securityName": "בינלאומי",
        "symbol": "בנלמ"
    },
    {
        "securityNumber": "1084557",
        "securityName": "נובה",
        "symbol": "נובה"
    },
    {
        "securityNumber": "1155290",
        "securityName": "אנרג'יאן",
        "symbol": "אנאג"
    },
    {
        "securityNumber": "767012",
        "securityName": "הפניקס",
        "symbol": "פנקס"
    },
    {
        "securityNumber": "323014",
        "securityName": "מליסרון",
        "symbol": "מלסרן"
    },
    {
        "securityNumber": "226019",
        "securityName": "מבנה",
        "symbol": "מבנה"
    },
    {
        "securityNumber": "390013",
        "securityName": "אלוני חץ",
        "symbol": "אלחץ"
    },
    {
        "securityNumber": "576017",
        "securityName": "חברה לישראל",
        "symbol": "חל"
    },
    {
        "securityNumber": "1097278",
        "securityName": "אמות",
        "symbol": "אמות"
    },
    {
        "securityNumber": "1097260",
        "securityName": "ביג",
        "symbol": "ביג"
    },
    {
        "securityNumber": "1141571",
        "securityName": "או פי סי אנרגיה",
        "symbol": "אפסא"
    },
    {
        "securityNumber": "1084128",
        "securityName": "דלק קבוצה",
        "symbol": "דלקקב"
    },
    {
        "securityNumber": "1133875",
        "securityName": "שפיר הנדסה",
        "symbol": "שפהנ"
    },
    {
        "securityNumber": "1095835",
        "securityName": "ארפורט סיטי",
        "symbol": "ארפט"
    },
    {
        "securityNumber": "739037",
        "securityName": "אלקטרה",
        "symbol": "אלקטה"
    },
    {
        "securityNumber": "746016",
        "securityName": "שטראוס",
        "symbol": "שטרס"
    },
    {
        "securityNumber": "475020",
        "securityName": "ניו-מד אנרג יהש",
        "symbol": "נומד"
    },
    {
        "securityNumber": "585018",
        "securityName": "הראל השקעות",
        "symbol": "הראל"
    }
]